django_horizontal_list_filter/__init__.py
django_horizontal_list_filter/apps.py
django_horizontal_list_filter/tests.py
django_horizontal_list_filter/locale/zh_Hans/LC_MESSAGES/django.mo
django_horizontal_list_filter/locale/zh_Hans/LC_MESSAGES/django.po
django_horizontal_list_filter/migrations/__init__.py
django_horizontal_list_filter/static/django-horizontal-list-filter/css/django-horizontal-list-filter.css
django_horizontal_list_filter/static/django-horizontal-list-filter/js/django-horizontal-list-filter-use-select2.js
django_horizontal_list_filter/static/django-horizontal-list-filter/js/django-horizontal-list-filter.js
django_horizontal_list_filter/templates/admin/change_list.html
django_horizontal_list_filter/templates/admin/filter.html
django_horizontal_list_filter/templates/admin/mptt_filter.html
django_horizontal_list_filter/templatetags/__init__.py
django_horizontal_list_filter/templatetags/django_horizontal_list_filter.py
django_horizontal_list_filter-0.2.10.dist-info/licenses/LICENSE
django_horizontal_list_filter-0.2.10.dist-info/METADATA
django_horizontal_list_filter-0.2.10.dist-info/WHEEL
django_horizontal_list_filter-0.2.10.dist-info/top_level.txt
django_horizontal_list_filter-0.2.10.dist-info/RECORD
